final_capstone/src/APB_bus_regs.v
module APB_bus_regs(
    input  wire        pclk,
    input  wire        preset_n,
    input  wire        psel,
    input  wire        penable,
    input  wire        pwrite,
    input  wire [7:0]  paddr,
    input  wire [31:0] pwdata,

    output reg  [31:0] prdata,
    output reg         pready,

    output reg  [31:0] velocity   
);

    wire [1:0] wordaddr;
    assign wordaddr = paddr[3:2];

    always @(posedge pclk or negedge preset_n) begin
        if (!preset_n) begin
            velocity <= 32'd0;
            pready   <= 1'b0;
            prdata   <= 32'd0;
        end else begin
            pready <= 1'b0;

            if (psel && !penable) begin
                pready <= 1'b1;

                if (pwrite) begin
                    case (wordaddr)
                        2'b00: velocity <= pwdata;  // 0x40002400
                    endcase
                end else begin
                    case (wordaddr)
                        2'b00: prdata <= velocity;
                        default: prdata <= 32'd0;
                    endcase
                end
            end
        end
    end

endmodule

final_capstone/bench/tb_APB_bus_regs.v
`timescale 1ns/1ps

module tb_APB_bus_regs;

reg         pclk;
reg         preset_n;
reg         psel;
reg         penable;
reg         pwrite;
reg [7:0]   paddr;
reg [31:0]  pwdata;

wire [31:0] prdata;
wire        pready;
wire [31:0] velocity;

// DUT
APB_bus_regs dut (
    .pclk(pclk),
    .preset_n(preset_n),
    .psel(psel),
    .penable(penable),
    .pwrite(pwrite),
    .paddr(paddr),
    .pwdata(pwdata),
    .prdata(prdata),
    .pready(pready),
    .velocity(velocity)
);

// clock 100MHz
always #5 pclk = ~pclk;

initial begin
    $dumpfile("apb_tb.vcd");
    $dumpvars(0, tb_APB_bus_regs);

    // init
    pclk = 0;
    preset_n = 0;
    psel = 0;
    penable = 0;
    pwrite = 0;
    paddr = 0;
    pwdata = 0;

    // ================= RESET =================
    #20;
    preset_n = 1;

    // ================= WRITE velocity =================
    #10;

    apb_write(8'h00, 32'h000003E8); // 1000

    #20;

    // ================= READ velocity =================
    apb_read(8'h00);

    #20;

    // ================= CHANGE VALUE =================
    apb_write(8'h00, 32'h00000FA0); // 4000

    #20;

    apb_read(8'h00);

    #50;

    $finish;
end

// ================= TASK: WRITE =================
task apb_write(input [7:0] addr, input [31:0] data);
begin
    @(posedge pclk);
    paddr   <= addr;
    pwdata  <= data;
    pwrite  <= 1;
    psel    <= 1;
    penable <= 0;

    @(posedge pclk);
    penable <= 1;

    @(posedge pclk);
    psel    <= 0;
    penable <= 0;
    pwrite  <= 0;
end
endtask

// ================= TASK: READ =================
task apb_read(input [7:0] addr);
begin
    @(posedge pclk);
    paddr   <= addr;
    pwrite  <= 0;
    psel    <= 1;
    penable <= 0;

    @(posedge pclk);
    penable <= 1;

    @(posedge pclk);
    psel    <= 0;
    penable <= 0;
end
endtask

endmodule

final_capstone/sim/apb_tb.vcd
$date
	Wed Jun 03 14:02:21 2026
$end
$version
	Icarus Verilog
$end
$timescale
	1ps
$end
$scope module tb_APB_bus_regs $end
$var wire 32 ! prdata [31:0] $end
$var wire 1 " pready $end
$var wire 32 # velocity [31:0] $end
$var reg 8 $ paddr [7:0] $end
$var reg 1 % pclk $end
$var reg 1 & penable $end
$var reg 1 ' preset_n $end
$var reg 1 ( psel $end
$var reg 32 ) pwdata [31:0] $end
$var reg 1 * pwrite $end
$scope module dut $end
$var wire 8 + paddr [7:0] $end
$var wire 1 , pclk $end
$var wire 1 - penable $end
$var wire 1 . preset_n $end
$var wire 1 / psel $end
$var wire 32 0 pwdata [31:0] $end
$var wire 1 1 pwrite $end
$var wire 2 2 wordaddr [1:0] $end
$var reg 32 3 prdata [31:0] $end
$var reg 1 4 pready $end
$var reg 32 5 velocity [31:0] $end
$upscope $end
$scope task apb_read $end
$var reg 8 6 addr [7:0] $end
$upscope $end
$scope task apb_write $end
$var reg 8 7 addr [7:0] $end
$var reg 32 8 data [31:0] $end
$upscope $end
$upscope $end
$enddefinitions $end
#0
$dumpvars
bx 8
bx 7
bx 6
b0 5
04
b0 3
b0 2
01
b0 0
0/
0.
0-
0,
b0 +
0*
b0 )
0(
0'
0&
0%
b0 $
b0 #
0"
b0 !
$end
#5000
1%
1,
#10000
0%
0,
#15000
1%
1,
#20000
0%
0,
1'
1.
#25000
1%
1,
#30000
0%
0,
b1111101000 8
b0 7
#35000
1(
1/
1*
11
b1111101000 )
b1111101000 0
1%
1,
#40000
0%
0,
#45000
b1111101000 5
b1111101000 #
14
1"
1&
1-
1%
1,
#50000
0%
0,
#55000
04
0"
0*
01
0&
0-
0(
0/
1%
1,
#60000
0%
0,
#65000
1%
1,
#70000
0%
0,
#75000
1(
1/
1%
1,
b0 6
#80000
0%
0,
#85000
b1111101000 3
b1111101000 !
14
1"
1&
1-
1%
1,
#90000
0%
0,
#95000
04
0"
0&
0-
0(
0/
1%
1,
#100000
0%
0,
#105000
1%
1,
#110000
0%
0,
#115000
1(
1/
1*
11
b111110100000 )
b111110100000 0
1%
1,
b111110100000 8
#120000
0%
0,
#125000
b111110100000 5
b111110100000 #
14
1"
1&
1-
1%
1,
#130000
0%
0,
#135000
04
0"
0*
01
0&
0-
0(
0/
1%
1,
#140000
0%
0,
#145000
1%
1,
#150000
0%
0,
#155000
1(
1/
1%
1,
#160000
0%
0,
#165000
b111110100000 3
b111110100000 !
14
1"
1&
1-
1%
1,
#170000
0%
0,
#175000
04
0"
0&
0-
0(
0/
1%
1,
