final_capstone/src/Single_p.v
module Single_p(
    input clk, rst,
    input oce, ce,
    input [9:0] ad,
    input we,
    input [15:0] Din,
    output [15:0] Dout
);

reg [15:0] mem [0:653];

reg [15:0] Do_pipe;
reg [15:0] Do;

initial begin
    $readmemh("ASCII_n_OVaddr.mem", mem);
end

always @(negedge clk) begin
    if (rst) begin
        Do_pipe <= 16'd0;
    end else if (ce) begin
        if (we) begin
            mem[ad] <= Din;
            Do_pipe <= Din;        // write-through
        end else begin
            Do_pipe <= mem[ad];   // read
        end

    end
end
always @(posedge clk) begin //output delay 1 cycle
            if (oce)
            Do <= Do_pipe;
end

assign Dout = Do;


endmodule

final_capstone/bench/tb_Single_p.v
`timescale 1ns / 1ps

module tb_Single_p;

    // Inputs to the UUT
    reg clk;
    reg rst;
    reg oce;
    reg ce;
    reg [9:0] ad;
    reg we;
    reg [15:0] Din;

    // Outputs from the UUT
    wire [15:0] Dout;

    // Instantiate the Unit Under Test (UUT)
    Single_p uut (
        .clk(clk),
        .rst(rst),
        .oce(oce),
        .ce(ce),
        .ad(ad),
        .we(we),
        .Din(Din),
        .Dout(Dout)
    );

    // Clock generation: 100MHz (10ns period)
    always #5 clk = ~clk;

    initial begin
        // --- Setup for Icarus Verilog Waveform Viewing ---
        $dumpfile("single_p_wave.vcd");
        $dumpvars(0, tb_Single_p);

        // --- Step 1: Initialize Signals ---
        clk  = 0;
        rst  = 1; // Active high reset
        oce  = 0;
        ce   = 0;
        we   = 0;
        ad   = 10'h000;
        Din  = 16'h0000;

        // Hold reset for 2 clock cycles
        #20;
        
        // Release reset and enable memory + output stage
        rst = 0;
        ce  = 1;
        oce = 1;
        #5;

        // --- Step 2: Read Test ---
        // Let's read from the first few addresses populated by your .mem file
        // Remember: operations trigger on falling edge (negedge clk), 
        // and Dout updates on the following rising edge (posedge clk).

        ad = 10'h000; #10; // Read address 0
        ad = 10'h001; #10; // Read address 1
        ad = 10'h002; #10; // Read address 2
        ad = 10'h003; #10; // Read address 3

        // --- Step 3: Write-Through Test ---
        // Let's write fresh values into memory. 
        // Because of 'write-through', Din should reflect onto Do_pipe instantly on negedge.
        
        we = 1; 
        ad = 10'h010; Din = 16'hAAAA; #10; 
        ad = 10'h011; Din = 16'hBBBB; #10;
        ad = 10'h012; Din = 16'hCCCC; #10;

        // --- Step 4: Verify the Writes via Reads ---
        we = 0;
        ad = 10'h010; #10;
        ad = 10'h011; #10;
        ad = 10'h012; #10;

        // Finish simulation
        #20;
        $finish;
    end

    // Monitor outputs in the terminal text console
    initial begin
        $monitor("Time=%0dt ns | rst=%b ce=%b we=%b | ad=%h Din=%h | Dout=%h", 
                 $time, rst, ce, we, ad, Din, Dout);
    end

endmodule

final_capstone/sim/single_p_wave.vcd
$date
	Thu Jun 04 00:32:02 2026
$end
$version
	Icarus Verilog
$end
$timescale
	1ps
$end
$scope module tb_Single_p $end
$var wire 16 ! Dout [15:0] $end
$var reg 16 " Din [15:0] $end
$var reg 10 # ad [9:0] $end
$var reg 1 $ ce $end
$var reg 1 % clk $end
$var reg 1 & oce $end
$var reg 1 ' rst $end
$var reg 1 ( we $end
$scope module uut $end
$var wire 16 ) Din [15:0] $end
$var wire 16 * Dout [15:0] $end
$var wire 10 + ad [9:0] $end
$var wire 1 , ce $end
$var wire 1 - clk $end
$var wire 1 . oce $end
$var wire 1 / rst $end
$var wire 1 0 we $end
$var reg 16 1 Do [15:0] $end
$var reg 16 2 Do_pipe [15:0] $end
$upscope $end
$upscope $end
$enddefinitions $end
#0
$dumpvars
b0 2
bx 1
00
1/
0.
0-
0,
b0 +
bx *
b0 )
0(
1'
0&
0%
0$
b0 #
b0 "
bx !
$end
#5000
1%
1-
#10000
0%
0-
#15000
1%
1-
#20000
0%
0-
1&
1.
1$
1,
0'
0/
#25000
b0 1
b0 !
b0 *
1%
1-
#30000
0%
0-
#35000
1%
1-
b1 #
b1 +
#40000
0%
0-
#45000
1%
1-
b10 #
b10 +
#50000
0%
0-
#55000
1%
1-
b11 #
b11 +
#60000
0%
0-
#65000
1%
1-
b1010101010101010 "
b1010101010101010 )
b10000 #
b10000 +
1(
10
#70000
b1010101010101010 2
0%
0-
#75000
b1010101010101010 1
b1010101010101010 !
b1010101010101010 *
1%
1-
b1011101110111011 "
b1011101110111011 )
b10001 #
b10001 +
#80000
b1011101110111011 2
0%
0-
#85000
b1011101110111011 1
b1011101110111011 !
b1011101110111011 *
1%
1-
b1100110011001100 "
b1100110011001100 )
b10010 #
b10010 +
#90000
b1100110011001100 2
0%
0-
#95000
b1100110011001100 1
b1100110011001100 !
b1100110011001100 *
1%
1-
b10000 #
b10000 +
0(
00
#100000
b1010101010101010 2
0%
0-
#105000
b1010101010101010 1
b1010101010101010 !
b1010101010101010 *
1%
1-
b10001 #
b10001 +
#110000
b1011101110111011 2
0%
0-
#115000
b1011101110111011 1
b1011101110111011 !
b1011101110111011 *
1%
1-
b10010 #
b10010 +
#120000
b1100110011001100 2
0%
0-
#125000
b1100110011001100 1
b1100110011001100 !
b1100110011001100 *
1%
1-
