final_capstone/src/testpattern.v
`timescale 1ns/1ps
module testpattern
(
    input               I_pxl_clk,   // pixel clock
    input               I_rst_n,     // low active
    input       [31:0]  Measured_val,
    input              in_key,
    input  wire        pclk,
    input  wire        preset_n,
    input  wire        psel,
    input  wire        penable,
    input  wire        pwrite,
    input  wire [7:0]  paddr,
    input  wire [31:0] pwdata,

    output reg  [31:0] prdata,
    output reg         pready,
    input       [9:0]   PIXDATA,
    input               PIXCLK,
    input               I_hs_pol,    // HS polarity
    input               I_vs_pol,    // VS polarity
    output      [11:0]  E_hcnt,
    output      [11:0]  E_vcnt,

    output              o_CLK565,
    //output reg          O_hs,
    output               V_pos,
    output reg          O_vs,
    output      [15:0]  O_data,      // rgb565 combined from out_color
    input               VSYNC,       // from camera
    input               HREF,         // from camera (acts as DE)
    input       [15:0]  word_o,
    output      [8:0]   word_addr
);


localparam N = 5; // pipeline length

localparam WHITE   = {8'd255, 8'd255, 8'd255}; 
localparam YELLOW  = {8'd255  , 8'd255, 8'd0};
localparam CYAN    = {8'd0, 8'd255, 8'd255  };
localparam GREEN   = {8'd0  , 8'd255, 8'd0  };
localparam MAGENTA = {8'd127, 8'd0  , 8'd127};
localparam RED     = {8'd127  , 8'd0  , 8'd0};
localparam BLUE    = {8'd0   , 8'd0  , 8'd255 };
localparam BLACK   = {8'd0  , 8'd0  , 8'd0  };

//-------------------------------------------------------------
// Internal signals
//-------------------------------------------------------------
reg  [11:0] h_cnt;
reg  [11:0] v_cnt;
  

wire [23:0] temp_cam24;  
assign temp_cam24 = { {PIXDAT565[15:11],3'b000},        
                      {PIXDAT565[10:5], 2'b00},         
                      {PIXDAT565[4:0], 3'b000} };       

//-------------------------------------------------------------

always @(posedge I_pxl_clk or negedge I_rst_n) begin
    if (!I_rst_n)
        h_cnt <= 12'd0;
    else if (!HREF)
        h_cnt <= 12'd0;
    else
        h_cnt <= h_cnt + 12'd1;
end

reg href_d1;
always @(posedge I_pxl_clk or negedge I_rst_n) begin
    if (!I_rst_n)
        href_d1 <= 1'b0;
    else
        href_d1 <= HREF;
end
wire href_fall = href_d1 & ~HREF;

always @(posedge I_pxl_clk or negedge I_rst_n) begin
    if (!I_rst_n)
        v_cnt <= 12'd0;
    else if (VSYNC)
        v_cnt <= 12'd0;
    else if (href_fall)
        v_cnt <= v_cnt + 12'd1;
end


reg [N-1:0] Pout_de_dn;
reg [N-1:0] Pout_hs_dn;
reg [N-1:0] Pout_vs_dn;

wire Pout_de_w = HREF;   
wire Pout_hs_w = HREF;   
wire Pout_vs_w = VSYNC;  

always @(posedge I_pxl_clk or negedge I_rst_n) begin
    if (!I_rst_n) begin
        Pout_de_dn <= {N{1'b0}};
        Pout_hs_dn <= {N{1'b1}};
        Pout_vs_dn <= {N{1'b1}};
    end else begin
        Pout_de_dn <= {Pout_de_dn[N-2:0], Pout_de_w};
        Pout_hs_dn <= {Pout_hs_dn[N-2:0], Pout_hs_w};
        Pout_vs_dn <= {Pout_vs_dn[N-2:0], Pout_vs_w};
    end
end

assign O_de = Pout_de_dn[4]; // tap chosen to align with pipeline (5 for index 4)
always @(posedge I_pxl_clk or negedge I_rst_n) begin
    if (!I_rst_n) begin
        //O_hs <= ~I_hs_pol;
        O_vs <= ~I_vs_pol;
    end else begin
        // map camera signals to HS/VS outputs with polarity selection
        //O_hs <= I_hs_pol ? ~Pout_hs_dn[3] : Pout_hs_dn[3];
        O_vs <= I_vs_pol ? ~Pout_vs_dn[3] : Pout_vs_dn[3];
    end
end


wire De_pos = ~Pout_de_dn[1] &  Pout_de_dn[0]; // DE rising 
wire De_neg =  Pout_de_dn[1] & ~Pout_de_dn[0]; // DE falling 
wire Vs_pos = ~Pout_vs_dn[1] &  Pout_vs_dn[0]; // VS rising 

assign V_pos= Vs_pos;
reg [11:0] De_hcnt;
reg [11:0] De_vcnt;

always @(posedge I_pxl_clk or negedge I_rst_n) begin
    if (!I_rst_n)
        De_hcnt <= 12'd0;
    else if (De_pos)
        De_hcnt <= 12'd0;
    else if (Pout_de_dn[1])
        De_hcnt <= De_hcnt + 12'd1;
    else
        De_hcnt <= De_hcnt;
end

always @(posedge I_pxl_clk or negedge I_rst_n) begin
    if (!I_rst_n)
        De_vcnt <= 12'd0;
    else if (Vs_pos)
        De_vcnt <= 12'd0;
    else if (De_neg)
        De_vcnt <= De_vcnt + 12'd1;
    else
        De_vcnt <= De_vcnt;
end
assign E_hcnt =De_hcnt;
assign E_vcnt =De_vcnt;
//-----------------------------------------------------------//
reg [9:0]  pixdata_d1; 
reg        PIXCLK565;
reg [15:0] PIXDAT565;
always @(posedge PIXCLK or negedge I_rst_n) //I_clk
begin
    if(!I_rst_n) begin
        pixdata_d1 <= 10'd0;
        PIXCLK565 <= 0;
    end else begin
        pixdata_d1 <= PIXDATA;
        if(~HREF) PIXCLK565 <= 0;
        else begin
            PIXCLK565 <= ~PIXCLK565;    // 1/2
            if(PIXCLK565) PIXDAT565[7:0] <= PIXDATA[9:2];
            else          PIXDAT565[15:8] <= PIXDATA[9:2];
        end
    end
end
assign o_CLK565=PIXCLK565;
//------------------------------------------------------------//
localparam dot_hor = 12'd1000;
localparam dot_ver = 12'd320;
localparam num_hor = 12'd900;
localparam num_ver = 12'd500;
localparam gps_hor = 12'd100;
localparam gps_ver = 12'd700;

localparam size = 25;
localparam size_num = 75;
localparam addr = 9'd0;//72



reg [23:0] cam_dot;
reg [11:0] dx, dy;

//wire [15:0] word_o;
//wire [8:0]  word_addr;
reg  [12:0] addr_base;

reg [15:0] logo_pixel_r;
reg odd_flag;
reg [9:0] digits [0:45];
reg [7:0] digit_sel=8'd0;
reg  [7:0] gps_buf [0:35];
reg [3:0] wr_idx;
reg gps_ready;
integer i;
wire [1:0] wordaddr;
assign wordaddr = paddr[3:2];


wire [23:0] mix_color = (temp_cam24 >>1)+ (WHITE>>2);
wire [23:0] blurry =(temp_cam24 )+ (WHITE>>1);
assign word_addr = addr_base;
/*
    Gowin_SP BSRAM_blk(
        .dout(word_o), //output [15:0] dout
        .clk(I_pxl_clk), //input clk
        .oce(1'b1), //input oce
        .ce(1'b1), //input ce
        .reset(1'b0), //input reset
        .wre(1'b0), //input wre
        .ad(word_addr), //input [8:0] ad
        .din(16'h0000) //input [15:0] din
    );*/
always @(posedge pclk or negedge preset_n) begin
        if (!preset_n) begin
            pready    <= 1'b0;
            prdata    <= 32'd0;
            wr_idx    <= 0;
            gps_ready <= 0;

            for (i = 0; i < 33; i = i + 1)
                gps_buf[i] <= 8'd0;

        end else begin
            pready <= 1'b0;
            gps_ready <= 0;

            if (psel && !penable) begin
                pready <= 1'b1;

                /* ===== WRITE ===== */
                if (pwrite) begin
                    case (wordaddr)

                        /* 0x00 → GPS DATA STREAM */
                        2'b00: begin
                            gps_buf[wr_idx*4 + 0] <= pwdata[7:0];
                            gps_buf[wr_idx*4 + 1] <= pwdata[15:8];
                            gps_buf[wr_idx*4 + 2] <= pwdata[23:16];
                            gps_buf[wr_idx*4 + 3] <= pwdata[31:24];

                            if (wr_idx == 4'd8) begin
                                wr_idx <= 0;
                                gps_ready <= 1'b1; // FULL FRAME DONE
                            end else begin
                                wr_idx <= wr_idx + 1;
                            end
                        end

                        /* 0x04 → CONTROL (optional reset) */
                        2'b01: begin
                            if (pwdata[0])
                                wr_idx <= 0;
                        end

                    endcase
                end

                /* ===== READ (debug) ===== */
                else begin
                    case (wordaddr)
                        2'b00: prdata <= {28'd0, wr_idx};
                        2'b01: prdata <= {31'd0, gps_ready};
                        default: prdata <= 32'd0;
                    endcase
                end
            end
        end
    end


always @(posedge I_pxl_clk) begin //stay still addr
    digits[0] <= Measured_val[31:24]+9'd64;
    digits[1] <= Measured_val[23:16]+9'd64;
    digits[2] <= 9'd56;
    digits[3] <= Measured_val[15:8]+9'd64;
    digits[4] <= Measured_val[7:0]+9'd64;
    digits[5] <= 9'd0;
    digits[6] <= 9'd172;
    digits[7] <= 9'd308;
    digits[8] <= 9'd60;
    digits[9] <= 9'd288;
    digits[5] <= 9'd0;
    digits[6] <= 9'd172;
    digits[7] <= 9'd308;
    digits[8] <= 9'd60;
    digits[9] <= 9'd288;
    if (gps_ready) begin
       for (i = 10; i < 45; i = i + 1)
           digits[i] <= gps_buf[i-10]*4 - 9'd128;//3'd4+9'd64;
    end
end
always @(posedge I_pxl_clk or negedge I_rst_n) begin
    if (!I_rst_n) begin
        cam_dot <= 0;
        dx <= 0; dy <= 0;
        addr_base <= 0;
        odd_flag <= 0;
        logo_pixel_r <= 0;
    end else begin
        logo_pixel_r <= word_o;

        if (De_hcnt >= dot_hor - size && De_hcnt < dot_hor + size &&
            De_vcnt >= dot_ver  && De_vcnt < dot_ver + size) begin

                cam_dot <= mix_color;

        end
        else if (De_hcnt >= num_hor && De_hcnt < num_hor+321 &&
                 De_vcnt >= num_ver && De_vcnt < num_ver+32) begin

            digit_sel <= (De_hcnt - num_hor) >> 5;
            //addr = digits[digit_sel];
            //num_hor_shift = num_hor + (digit_sel << 3);

            dx <= (De_hcnt - (num_hor + (digit_sel << 5)))>>2;
            dy <= (De_vcnt - num_ver)>>2;
        
            addr_base <= digits[digit_sel]+(dy>>1);//((De_vcnt - num_ver) >> 1);
            odd_flag <= dy & 1;//(De_vcnt - num_ver) & 1;

            if (dx < 8 && dy < 8) begin
                if (odd_flag)
                    cam_dot <= logo_pixel_r[7 - dx] ? mix_color: temp_cam24;
                else
                    cam_dot <= logo_pixel_r[15 - dx] ? mix_color : temp_cam24;
            end 
        end
        else if (De_hcnt >= gps_hor && De_hcnt < gps_hor+/*1665*/ 1153 &&
                 De_vcnt >= gps_ver && De_vcnt < gps_ver+32) begin
                    //cam_dot<= BLUE;
            digit_sel <= (De_hcnt - gps_hor) >> 5;
            dx <= (De_hcnt - (gps_hor + (digit_sel << 5)))>>2;
            dy <= (De_vcnt - gps_ver)>>2;
        
            addr_base <= digits[digit_sel+10]+(dy>>1);
            odd_flag <= dy & 1;

            if (dx < 8 && dy < 8) begin
                if (odd_flag)
                    cam_dot <= logo_pixel_r[7 - dx] ? mix_color: temp_cam24;
                else
                    cam_dot <= logo_pixel_r[15 - dx] ? mix_color : temp_cam24;
            end
        end
        else begin
                cam_dot <= temp_cam24;
            end
    end
end


//==============//
assign O_data ={ cam_dot[23:19], cam_dot[15:10], cam_dot[7:3] };
endmodule

final_capstone/bench/tb_testpattern.v
`timescale 1ns/1ps

module tb_testpattern;

reg         I_pxl_clk;
reg         I_rst_n;

reg  [31:0] Measured_val;
reg         in_key;

reg         pclk;
reg         preset_n;
reg         psel;
reg         penable;
reg         pwrite;
reg  [7:0]  paddr;
reg  [31:0] pwdata;

reg  [9:0]  PIXDATA;
reg         PIXCLK;
reg         HREF;
reg         VSYNC;

wire [31:0] prdata;
wire        pready;
wire [11:0] E_hcnt;
wire [11:0] E_vcnt;
wire        o_CLK565;
wire        V_pos;
wire        O_vs;
wire [15:0] O_data;
wire [8:0]  word_addr;

// DUT
testpattern dut (
    .I_pxl_clk(I_pxl_clk),
    .I_rst_n(I_rst_n),
    .Measured_val(Measured_val),
    .in_key(in_key),

    .pclk(pclk),
    .preset_n(preset_n),
    .psel(psel),
    .penable(penable),
    .pwrite(pwrite),
    .paddr(paddr),
    .pwdata(pwdata),
    .prdata(prdata),
    .pready(pready),

    .PIXDATA(PIXDATA),
    .PIXCLK(PIXCLK),
    .HREF(HREF),
    .VSYNC(VSYNC),

    .E_hcnt(E_hcnt),
    .E_vcnt(E_vcnt),
    .o_CLK565(o_CLK565),
    .V_pos(V_pos),
    .O_vs(O_vs),
    .O_data(O_data),
    .word_o(16'hA5A5),
    .word_addr(word_addr)
);

// ================= CLOCKS =================
initial begin
    I_pxl_clk = 0;
    forever #10 I_pxl_clk = ~I_pxl_clk; // 50MHz pixel clock
end

initial begin
    PIXCLK = 0;
    forever #20 PIXCLK = ~PIXCLK; // camera clock slower
end

initial begin
    pclk = 0;
    forever #5 pclk = ~pclk; // APB clock 100MHz
end

// ================= RESET =================
initial begin
    I_rst_n = 0;
    preset_n = 0;

    HREF = 0;
    VSYNC = 1;
    PIXDATA = 0;

    Measured_val = 32'h12345678;
    in_key = 0;

    psel = 0;
    penable = 0;
    pwrite = 0;
    paddr = 0;
    pwdata = 0;

    #100;
    I_rst_n = 1;
    preset_n = 1;
end

// ================= CAMERA STIMULUS =================
reg [9:0] pixel_cnt;

always @(posedge PIXCLK) begin
    if (!I_rst_n) begin
        PIXDATA <= 0;
        HREF <= 0;
        VSYNC <= 1;
        pixel_cnt <= 0;
    end else begin

        VSYNC <= 0;
        HREF  <= 1;

        // fake grayscale ramp
        PIXDATA <= pixel_cnt;

        pixel_cnt <= pixel_cnt + 1;

        // simulate line break
        if (pixel_cnt == 300) begin
            HREF <= 0;
        end
    end
end

// ================= APB WRITE TEST =================
initial begin
    #200;

    apb_write(8'h00, 32'h11223344);
    apb_write(8'h04, 32'h00000001);

    #500;

    apb_write(8'h00, 32'hAABBCCDD);
end

task apb_write(input [7:0] addr, input [31:0] data);
begin
    @(posedge pclk);
    paddr = addr;
    pwdata = data;
    pwrite = 1;
    psel = 1;
    penable = 0;

    @(posedge pclk);
    penable = 1;

    @(posedge pclk);
    psel = 0;
    penable = 0;
    pwrite = 0;
end
endtask

// ================= WAVEFORM =================
initial begin
    $dumpfile("testpattern.vcd");
    $dumpvars(0, tb_testpattern);
end

// ================= END =================
initial begin
    #5000;
    $finish;
end

endmodule

final_capstone/sim/testpattern.vcd
$date
	Wed Jun 03 16:05:04 2026
$end
$version
	Icarus Verilog
$end
$timescale
	1ps
$end
$scope module tb_testpattern $end
$var wire 12 ! E_hcnt [11:0] $end
$var wire 12 " E_vcnt [11:0] $end
$var wire 16 # O_data [15:0] $end
$var wire 1 $ O_vs $end
$var wire 1 % V_pos $end
$var wire 1 & o_CLK565 $end
$var wire 32 ' prdata [31:0] $end
$var wire 1 ( pready $end
$var wire 9 ) word_addr [8:0] $end
$var reg 1 * HREF $end
$var reg 1 + I_pxl_clk $end
$var reg 1 , I_rst_n $end
$var reg 32 - Measured_val [31:0] $end
$var reg 1 . PIXCLK $end
$var reg 10 / PIXDATA [9:0] $end
$var reg 1 0 VSYNC $end
$var reg 1 1 in_key $end
$var reg 8 2 paddr [7:0] $end
$var reg 1 3 pclk $end
$var reg 1 4 penable $end
$var reg 10 5 pixel_cnt [9:0] $end
$var reg 1 6 preset_n $end
$var reg 1 7 psel $end
$var reg 32 8 pwdata [31:0] $end
$var reg 1 9 pwrite $end
$scope module dut $end
$var wire 1 : De_neg $end
$var wire 1 ; De_pos $end
$var wire 12 < E_hcnt [11:0] $end
$var wire 12 = E_vcnt [11:0] $end
$var wire 1 > HREF $end
$var wire 1 ? I_hs_pol $end
$var wire 1 @ I_pxl_clk $end
$var wire 1 A I_rst_n $end
$var wire 1 B I_vs_pol $end
$var wire 32 C Measured_val [31:0] $end
$var wire 16 D O_data [15:0] $end
$var wire 1 E O_de $end
$var wire 1 F PIXCLK $end
$var wire 10 G PIXDATA [9:0] $end
$var wire 1 H Pout_de_w $end
$var wire 1 I Pout_hs_w $end
$var wire 1 J Pout_vs_w $end
$var wire 1 K VSYNC $end
$var wire 1 % V_pos $end
$var wire 1 L Vs_pos $end
$var wire 24 M blurry [23:0] $end
$var wire 1 N href_fall $end
$var wire 1 O in_key $end
$var wire 24 P mix_color [23:0] $end
$var wire 1 & o_CLK565 $end
$var wire 8 Q paddr [7:0] $end
$var wire 1 R pclk $end
$var wire 1 S penable $end
$var wire 1 T preset_n $end
$var wire 1 U psel $end
$var wire 32 V pwdata [31:0] $end
$var wire 1 W pwrite $end
$var wire 24 X temp_cam24 [23:0] $end
$var wire 9 Y word_addr [8:0] $end
$var wire 16 Z word_o [15:0] $end
$var wire 2 [ wordaddr [1:0] $end
$var reg 12 \ De_hcnt [11:0] $end
$var reg 12 ] De_vcnt [11:0] $end
$var reg 1 ^ O_vs $end
$var reg 1 _ PIXCLK565 $end
$var reg 16 ` PIXDAT565 [15:0] $end
$var reg 5 a Pout_de_dn [4:0] $end
$var reg 5 b Pout_hs_dn [4:0] $end
$var reg 5 c Pout_vs_dn [4:0] $end
$var reg 13 d addr_base [12:0] $end
$var reg 24 e cam_dot [23:0] $end
$var reg 8 f digit_sel [7:0] $end
$var reg 12 g dx [11:0] $end
$var reg 12 h dy [11:0] $end
$var reg 1 i gps_ready $end
$var reg 12 j h_cnt [11:0] $end
$var reg 1 k href_d1 $end
$var integer 32 l i [31:0] $end
$var reg 16 m logo_pixel_r [15:0] $end
$var reg 1 n odd_flag $end
$var reg 10 o pixdata_d1 [9:0] $end
$var reg 32 p prdata [31:0] $end
$var reg 1 q pready $end
$var reg 12 r v_cnt [11:0] $end
$var reg 4 s wr_idx [3:0] $end
$upscope $end
$scope task apb_write $end
$var reg 8 t addr [7:0] $end
$var reg 32 u data [31:0] $end
$upscope $end
$upscope $end
$enddefinitions $end
#0
$dumpvars
bx u
bx t
b0 s
b0 r
0q
b0 p
b0 o
0n
b0 m
b100001 l
0k
b0 j
0i
b0 h
b0 g
b0 f
b0 e
b0 d
b11111 c
b11111 b
b0 a
bx `
0_
x^
b0 ]
b0 \
b0 [
b1010010110100101 Z
b0 Y
bx000xxxxxx00xxxxx000 X
0W
b0 V
0U
0T
0S
0R
b0 Q
bx P
0O
0N
bx M
0L
1K
1J
0I
0H
b0 G
0F
0E
b0 D
b10010001101000101011001111000 C
zB
0A
0@
z?
0>
b0 =
b0 <
0;
0:
09
b0 8
07
06
bx 5
04
03
b0 2
01
10
b0 /
0.
b10010001101000101011001111000 -
0,
0+
0*
b0 )
0(
b0 '
0&
0%
x$
b0 #
b0 "
b0 !
$end
#5000
b100001 l
13
1R
#10000
03
0R
1+
1@
#15000
b100001 l
13
1R
#20000
b0 5
03
0R
0+
0@
1.
1F
#25000
b100001 l
13
1R
#30000
03
0R
1+
1@
#35000
b100001 l
13
1R
#40000
03
0R
0+
0@
0.
0F
#45000
b100001 l
13
1R
#50000
03
0R
1+
1@
#55000
b100001 l
13
1R
#60000
03
0R
0+
0@
1.
1F
#65000
b100001 l
13
1R
#70000
03
0R
1+
1@
#75000
b100001 l
13
1R
#80000
03
0R
0+
0@
0.
0F
#85000
b100001 l
13
1R
#90000
03
0R
1+
1@
#95000
b100001 l
13
1R
#100000
b1 5
1*
1H
1I
1>
00
0J
0K
03
0R
0+
0@
1.
1F
16
1T
1,
1A
#105000
13
1R
#110000
1;
bx #
bx D
b1 j
1k
b11110 c
b1 a
bx000xxxxxx00xxxxx000 e
b1010010110100101 m
03
0R
1+
1@
#115000
13
1R
#120000
03
0R
0+
0@
0.
0F
#125000
13
1R
#130000
0;
b11100 c
b11 a
b10 j
03
0R
1+
1@
#135000
13
1R
#140000
b0xxx00xxxxx000 X
b0xxxxxxxx `
1_
1&
b10 5
b1 /
b1 G
03
0R
0+
0@
1.
1F
#145000
13
1R
#150000
b0xxxxxxxx #
b0xxxxxxxx D
b11 j
b11000 c
b111 a
b1 \
b1 !
b1 <
b0xxx00xxxxx000 e
03
0R
1+
1@
#155000
13
1R
#160000
03
0R
0+
0@
0.
0F
#165000
13
1R
#170000
b10 \
b10 !
b10 <
b10000 c
b1111 a
b100 j
03
0R
1+
1@
#175000
13
1R
#180000
b1111111111111111111111 P
b11111111111111111111111 M
b0 X
b0 `
0_
0&
b1 o
b11 5
b10 /
b10 G
03
0R
0+
0@
1.
1F
#185000
13
1R
#190000
1E
b0 #
b0 D
b101 j
b0 c
b11111 a
b11 \
b11 !
b11 <
b0 e
03
0R
1+
1@
#195000
13
1R
#200000
03
0R
0+
0@
0.
0F
b10001001000100011001101000100 u
b0 t
#205000
b1 s
1q
1(
17
1U
19
1W
b10001001000100011001101000100 8
b10001001000100011001101000100 V
13
1R
#210000
b100 \
b100 !
b100 <
b110 j
03
0R
1+
1@
#215000
0q
0(
14
1S
13
1R
#220000
b0 `
1_
1&
b10 o
b100 5
b11 /
b11 G
03
0R
0+
0@
1.
1F
#225000
b1 u
b100 t
09
0W
04
0S
07
0U
13
1R
#230000
b111 j
b101 \
b101 !
b101 <
03
0R
1+
1@
#235000
b10 s
1q
1(
b1 [
17
1U
19
1W
b1 8
b1 V
b100 2
b100 Q
13
1R
#240000
03
0R
0+
0@
0.
0F
#245000
0q
0(
14
1S
13
1R
#250000
b110 \
b110 !
b110 <
b1000 j
03
0R
1+
1@
#255000
09
0W
04
0S
07
0U
13
1R
#260000
b0 `
0_
0&
b11 o
b101 5
b100 /
b100 G
03
0R
0+
0@
1.
1F
#265000
13
1R
#270000
b1001 j
b111 \
b111 !
b111 <
03
0R
1+
1@
#275000
13
1R
#280000
03
0R
0+
0@
0.
0F
#285000
13
1R
#290000
b1000 \
b1000 !
b1000 <
b1010 j
03
0R
1+
1@
#295000
13
1R
#300000
b10000000000111111111111 P
b100000000001111111111111 M
b10000000000000 X
b100000000 `
1_
1&
b100 o
b110 5
b101 /
b101 G
03
0R
0+
0@
1.
1F
#305000
13
1R
#310000
b100000000 #
b100000000 D
b1011 j
b1001 \
b1001 !
b1001 <
b10000000000000 e
03
0R
1+
1@
#315000
13
1R
#320000
03
0R
0+
0@
0.
0F
#325000
13
1R
#330000
b1010 \
b1010 !
b1010 <
b1100 j
03
0R
1+
1@
#335000
13
1R
#340000
b10000000001000000000011 P
b100000000010000000000111 M
b10000000001000 X
b100000001 `
0_
0&
b101 o
b111 5
b110 /
b110 G
03
0R
0+
0@
1.
1F
#345000
13
1R
#350000
b100000001 #
b100000001 D
b1101 j
b1011 \
b1011 !
b1011 <
b10000000001000 e
03
0R
1+
1@
#355000
13
1R
#360000
03
0R
0+
0@
0.
0F
#365000
13
1R
#370000
b1100 \
b1100 !
b1100 <
b1110 j
03
0R
1+
1@
#375000
13
1R
#380000
b100000001 `
1_
1&
b110 o
b1000 5
b111 /
b111 G
03
0R
0+
0@
1.
1F
#385000
13
1R
#390000
b1111 j
b1101 \
b1101 !
b1101 <
03
0R
1+
1@
#395000
13
1R
#400000
03
0R
0+
0@
0.
0F
#405000
13
1R
#410000
b1110 \
b1110 !
b1110 <
b10000 j
03
0R
1+
1@
#415000
13
1R
#420000
b100000001 `
0_
0&
b111 o
b1001 5
b1000 /
b1000 G
03
0R
0+
0@
1.
1F
#425000
13
1R
#430000
b10001 j
b1111 \
b1111 !
b1111 <
03
0R
1+
1@
#435000
13
1R
#440000
03
0R
0+
0@
0.
0F
#445000
13
1R
#450000
b10000 \
b10000 !
b10000 <
b10010 j
03
0R
1+
1@
#455000
13
1R
#460000
b10000000010000000000011 P
b100000000100000000000111 M
b100000000001000 X
b1000000001 `
1_
1&
b1000 o
b1010 5
b1001 /
b1001 G
03
0R
0+
0@
1.
1F
#465000
13
1R
#470000
b1000000001 #
b1000000001 D
b10011 j
b10001 \
b10001 !
b10001 <
b100000000001000 e
03
0R
1+
1@
#475000
13
1R
#480000
03
0R
0+
0@
0.
0F
#485000
13
1R
#490000
b10010 \
b10010 !
b10010 <
b10100 j
03
0R
1+
1@
#495000
13
1R
#500000
b10000000010000000000111 P
b100000000100000000001111 M
b100000000010000 X
b1000000010 `
0_
0&
b1001 o
b1011 5
b1010 /
b1010 G
03
0R
0+
0@
1.
1F
#505000
13
1R
#510000
b1000000010 #
b1000000010 D
b10101 j
b10011 \
b10011 !
b10011 <
b100000000010000 e
03
0R
1+
1@
#515000
13
1R
#520000
03
0R
0+
0@
0.
0F
#525000
13
1R
#530000
b10100 \
b10100 !
b10100 <
b10110 j
03
0R
1+
1@
#535000
13
1R
#540000
b1000000010 `
1_
1&
b1010 o
b1100 5
b1011 /
b1011 G
03
0R
0+
0@
1.
1F
#545000
13
1R
#550000
b10111 j
b10101 \
b10101 !
b10101 <
03
0R
1+
1@
#555000
13
1R
#560000
03
0R
0+
0@
0.
0F
#565000
13
1R
#570000
b10110 \
b10110 !
b10110 <
b11000 j
03
0R
1+
1@
#575000
13
1R
#580000
b1000000010 `
0_
0&
b1011 o
b1101 5
b1100 /
b1100 G
03
0R
0+
0@
1.
1F
#585000
13
1R
#590000
b11001 j
b10111 \
b10111 !
b10111 <
03
0R
1+
1@
#595000
13
1R
#600000
03
0R
0+
0@
0.
0F
#605000
13
1R
#610000
b11000 \
b11000 !
b11000 <
b11010 j
03
0R
1+
1@
#615000
13
1R
#620000
b10000000011000000000111 P
b100000000110000000001111 M
b110000000010000 X
b1100000010 `
1_
1&
b1100 o
b1110 5
b1101 /
b1101 G
03
0R
0+
0@
1.
1F
#625000
13
1R
#630000
b1100000010 #
b1100000010 D
b11011 j
b11001 \
b11001 !
b11001 <
b110000000010000 e
03
0R
1+
1@
#635000
13
1R
#640000
03
0R
0+
0@
0.
0F
#645000
13
1R
#650000
b11010 \
b11010 !
b11010 <
b11100 j
03
0R
1+
1@
#655000
13
1R
#660000
b10000000011000000001011 P
b100000000110000000010111 M
b110000000011000 X
b1100000011 `
0_
0&
b1101 o
b1111 5
b1110 /
b1110 G
03
0R
0+
0@
1.
1F
#665000
13
1R
#670000
b1100000011 #
b1100000011 D
b11101 j
b11011 \
b11011 !
b11011 <
b110000000011000 e
03
0R
1+
1@
#675000
13
1R
#680000
03
0R
0+
0@
0.
0F
#685000
13
1R
#690000
b11100 \
b11100 !
b11100 <
b11110 j
03
0R
1+
1@
#695000
13
1R
#700000
b1100000011 `
1_
1&
b1110 o
b10000 5
b1111 /
b1111 G
03
0R
0+
0@
1.
1F
#705000
13
1R
#710000
b11111 j
b11101 \
b11101 !
b11101 <
03
0R
1+
1@
#715000
13
1R
#720000
03
0R
0+
0@
0.
0F
#725000
13
1R
#730000
b11110 \
b11110 !
b11110 <
b100000 j
03
0R
1+
1@
#735000
13
1R
#740000
b1100000011 `
0_
0&
b1111 o
b10001 5
b10000 /
b10000 G
03
0R
0+
0@
1.
1F
#745000
13
1R
#750000
b100001 j
b11111 \
b11111 !
b11111 <
03
0R
1+
1@
#755000
b0 s
1q
1(
b0 [
17
1U
19
1W
b10101010101110111100110011011101 8
b10101010101110111100110011011101 V
b0 2
b0 Q
13
1R
b10101010101110111100110011011101 u
b0 t
#760000
03
0R
0+
0@
0.
0F
#765000
0q
0(
14
1S
13
1R
#770000
b100000 \
b100000 !
b100000 <
b100010 j
03
0R
1+
1@
#775000
09
0W
04
0S
07
0U
13
1R
#780000
b10000000100000000001011 P
b100000001000000000010111 M
b1000000000011000 X
b10000000011 `
1_
1&
b10000 o
b10010 5
b10001 /
b10001 G
03
0R
0+
0@
1.
1F
#785000
13
1R
#790000
b10000000011 #
b10000000011 D
b100011 j
b100001 \
b100001 !
b100001 <
b1000000000011000 e
03
0R
1+
1@
#795000
13
1R
#800000
03
0R
0+
0@
0.
0F
#805000
13
1R
#810000
b100010 \
b100010 !
b100010 <
b100100 j
03
0R
1+
1@
#815000
13
1R
#820000
b10000000100000000001111 P
b100000001000000000011111 M
b1000000000100000 X
b10000000100 `
0_
0&
b10001 o
b10011 5
b10010 /
b10010 G
03
0R
0+
0@
1.
1F
#825000
13
1R
#830000
b10000000100 #
b10000000100 D
b100101 j
b100011 \
b100011 !
b100011 <
b1000000000100000 e
03
0R
1+
1@
#835000
13
1R
#840000
03
0R
0+
0@
0.
0F
#845000
13
1R
#850000
b100100 \
b100100 !
b100100 <
b100110 j
03
0R
1+
1@
#855000
13
1R
#860000
b10000000100 `
1_
1&
b10010 o
b10100 5
b10011 /
b10011 G
03
0R
0+
0@
1.
1F
#865000
13
1R
#870000
b100111 j
b100101 \
b100101 !
b100101 <
03
0R
1+
1@
#875000
13
1R
#880000
03
0R
0+
0@
0.
0F
#885000
13
1R
#890000
b100110 \
b100110 !
b100110 <
b101000 j
03
0R
1+
1@
#895000
13
1R
#900000
b10000000100 `
0_
0&
b10011 o
b10101 5
b10100 /
b10100 G
03
0R
0+
0@
1.
1F
#905000
13
1R
#910000
b101001 j
b100111 \
b100111 !
b100111 <
03
0R
1+
1@
#915000
13
1R
#920000
03
0R
0+
0@
0.
0F
#925000
13
1R
#930000
b101000 \
b101000 !
b101000 <
b101010 j
03
0R
1+
1@
#935000
13
1R
#940000
b10000000101000000001111 P
b100000001010000000011111 M
b1010000000100000 X
b10100000100 `
1_
1&
b10100 o
b10110 5
b10101 /
b10101 G
03
0R
0+
0@
1.
1F
#945000
13
1R
#950000
b10100000100 #
b10100000100 D
b101011 j
b101001 \
b101001 !
b101001 <
b1010000000100000 e
03
0R
1+
1@
#955000
13
1R
#960000
03
0R
0+
0@
0.
0F
#965000
13
1R
#970000
b101010 \
b101010 !
b101010 <
b101100 j
03
0R
1+
1@
#975000
13
1R
#980000
b10000000101000000010011 P
b100000001010000000100111 M
b1010000000101000 X
b10100000101 `
0_
0&
b10101 o
b10111 5
b10110 /
b10110 G
03
0R
0+
0@
1.
1F
#985000
13
1R
#990000
b10100000101 #
b10100000101 D
b101101 j
b101011 \
b101011 !
b101011 <
b1010000000101000 e
03
0R
1+
1@
#995000
13
1R
#1000000
03
0R
0+
0@
0.
0F
#1005000
13
1R
#1010000
b101100 \
b101100 !
b101100 <
b101110 j
03
0R
1+
1@
#1015000
13
1R
#1020000
b10100000101 `
1_
1&
b10110 o
b11000 5
b10111 /
b10111 G
03
0R
0+
0@
1.
1F
#1025000
13
1R
#1030000
b101111 j
b101101 \
b101101 !
b101101 <
03
0R
1+
1@
#1035000
13
1R
#1040000
03
0R
0+
0@
0.
0F
#1045000
13
1R
#1050000
b101110 \
b101110 !
b101110 <
b110000 j
03
0R
1+
1@
#1055000
13
1R
#1060000
b10100000101 `
0_
0&
b10111 o
b11001 5
b11000 /
b11000 G
03
0R
0+
0@
1.
1F
#1065000
13
1R
#1070000
b110001 j
b101111 \
b101111 !
b101111 <
03
0R
1+
1@
#1075000
13
1R
