final_capstone/src/Semi_dual_port.v
module Semi_dual_port(
input clkA,
input clkB,
input oce,
input ceA,
input ceB,
input rstA,
input rstB,
input [9:0]addrA,
input [9:0]addrB,
input [15:0]dat_in,
output [15:0]dat_out
);
endmodule
/*
    input clkA, clkB, rst,
    input oce, ceA, ceB,
    input [9:0] adA, adB,
    input weA, weB,
    input [15:0] Din,
    output [15:0] DoutA, DoutB
);

reg [15:0] mem [0:653];

// pipeline registers
reg [15:0] DoA_pipe, DoB_pipe;
reg [15:0] DoA, DoB;


//PortA
always @(negedge clkA) begin
    if (rst) begin
        DoA_pipe <= 16'd0;
    end else if (ceA) begin
        if (weA) begin
            mem[adA] <= Din;
            DoA_pipe <= Din;        // write-through
        end else begin
            DoA_pipe <= mem[adA];   // read
        end

    end
end
always @(posedge clkA) begin //output delay 1 cycle
            if (oce)
            DoA <= DoA_pipe;
end
//PortB

always @(negedge clkB) begin //also with PB
    if (rst) begin
        DoB_pipe <= 16'd0;
    end else if (ceB) begin
        if (weB) begin
            mem[adB] <= Din;
            DoB_pipe <= Din;
        end else begin
            DoB_pipe <= mem[adB];
        end


    end
end
always @(posedge clkB) begin
        if (oce)
            DoB <= DoB_pipe;
end

assign DoutA = DoA;
assign DoutB = DoB;

endmodule*/

final_capstone/bench/tb_Semi_dual_port.v
`timescale 1ns / 1ps

module tb_Semi_dual_port;

    // Inputs to the UUT
    reg clkA;
    reg clkB;
    reg oce;
    reg ceA;
    reg ceB;
    reg rstA;
    reg rstB;
    reg [9:0] addrA;
    reg [9:0] addrB;
    reg [15:0] dat_in;

    // Outputs from the UUT
    wire [15:0] dat_out;

    // Instantiate the Unit Under Test (UUT)
    Semi_dual_port uut (
        .clkA(clkA),
        .clkB(clkB),
        .oce(oce),
        .ceA(ceA),
        .ceB(ceB),
        .rstA(rstA),
        .rstB(rstB),
        .addrA(addrA),
        .addrB(addrB),
        .dat_in(dat_in),
        .dat_out(dat_out)
    );

    // Clock generation: 100MHz clocks (10ns period) matching the waveform
    always #5 clkA = ~clkA;
    always #5 clkB = ~clkB;

    initial begin
        // --- Step 1: Initialize Inputs ---
        clkA  = 0;
        clkB  = 0;
        oce   = 0;
        ceA   = 0;
        ceB   = 0;
        rstA  = 1; // Start with reset active as seen early in waveforms
        rstB  = 1;
        addrA = 10'h000;
        addrB = 10'h000;
        dat_in = 16'h0000;

        // Hold reset for a couple of cycles
        #15;
        
        // --- Step 2: Release Reset & Enable Chip ---
        rstA = 0;
        rstB = 0;
        ceA  = 1;
        ceB  = 1;
        oce  = 1;
        #5;

        // --- Step 3: Write and Read Sequences ---
        // We write to AddrA and read from AddrB with a 1-cycle offset 
        // to mimic your wave pipeline structure.

        // Cycle 1
        addrA = 10'h001; dat_in = 16'h00FF;
        addrB = 10'h000;
        #10;

        // Cycle 2
        addrA = 10'h002; dat_in = 16'h00FA;
        addrB = 10'h001; 
        #10;

        // Cycle 3
        addrA = 10'h003; dat_in = 16'h00AB;
        addrB = 10'h002;
        #10;

        // Cycle 4
        addrA = 10'h004; dat_in = 16'h0015;
        addrB = 10'h003;
        #10;

        // Cycle 5
        addrA = 10'h005; dat_in = 16'h00F1;
        addrB = 10'h004;
        #10;

        // Cycle 6
        addrA = 10'h006; dat_in = 16'h00FF;
        addrB = 10'h005;
        #10;

        // Cycle 7
        addrA = 10'h007; dat_in = 16'h00FA;
        addrB = 10'h006;
        #10;

        // Cycle 8
        addrA = 10'h008; dat_in = 16'h00AB;
        addrB = 10'h007;
        #10;

        // Cycle 9
        addrA = 10'h009; dat_in = 16'h0015;
        addrB = 10'h008;
        #10;

        // Cycle 10
        addrA = 10'h00A; dat_in = 16'h00F1;
        addrB = 10'h009;
        #10;

        // Let simulation run a bit longer to witness final outputs propagate
        #50;
        
        $finish;
    end

    // Optional: Monitor results in the console window
    initial begin
        $monitor("Time=%0dt ns | addrA=%h dat_in=%h | addrB=%h dat_out=%h", 
                 $time, addrA, dat_in, addrB, dat_out);
    end
initial begin
    $dumpfile("waveform.vcd"); // Names the waveform dump file
    $dumpvars(0, tb_Semi_dual_port); // Dumps all variables in the testbench
end
endmodule

final_capstone/sim/waveform.vcd
$date
	Thu Jun 04 00:24:10 2026
$end
$version
	Icarus Verilog
$end
$timescale
	1ps
$end
$scope module tb_Semi_dual_port $end
$var wire 16 ! dat_out [15:0] $end
$var reg 10 " addrA [9:0] $end
$var reg 10 # addrB [9:0] $end
$var reg 1 $ ceA $end
$var reg 1 % ceB $end
$var reg 1 & clkA $end
$var reg 1 ' clkB $end
$var reg 16 ( dat_in [15:0] $end
$var reg 1 ) oce $end
$var reg 1 * rstA $end
$var reg 1 + rstB $end
$scope module uut $end
$var wire 10 , addrA [9:0] $end
$var wire 10 - addrB [9:0] $end
$var wire 1 . ceA $end
$var wire 1 / ceB $end
$var wire 1 0 clkA $end
$var wire 1 1 clkB $end
$var wire 16 2 dat_in [15:0] $end
$var wire 16 3 dat_out [15:0] $end
$var wire 1 4 oce $end
$var wire 1 5 rstA $end
$var wire 1 6 rstB $end
$upscope $end
$upscope $end
$enddefinitions $end
#0
$dumpvars
16
15
04
bz 3
b0 2
01
00
0/
0.
b0 -
b0 ,
1+
1*
0)
b0 (
0'
0&
0%
0$
b0 #
b0 "
bz !
$end
#5000
1'
11
1&
10
#10000
0'
01
0&
00
#15000
1'
11
1&
10
1)
14
1%
1/
1$
1.
0+
06
0*
05
#20000
0'
01
0&
00
b11111111 (
b11111111 2
b1 "
b1 ,
#25000
1'
11
1&
10
#30000
0'
01
0&
00
b1 #
b1 -
b11111010 (
b11111010 2
b10 "
b10 ,
#35000
1'
11
1&
10
#40000
0'
01
0&
00
b10 #
b10 -
b10101011 (
b10101011 2
b11 "
b11 ,
#45000
1'
11
1&
10
#50000
0'
01
0&
00
b11 #
b11 -
b10101 (
b10101 2
b100 "
b100 ,
#55000
1'
11
1&
10
#60000
0'
01
0&
00
b100 #
b100 -
b11110001 (
b11110001 2
b101 "
b101 ,
#65000
1'
11
1&
10
#70000
0'
01
0&
00
b101 #
b101 -
b11111111 (
b11111111 2
b110 "
b110 ,
#75000
1'
11
1&
10
#80000
0'
01
0&
00
b110 #
b110 -
b11111010 (
b11111010 2
b111 "
b111 ,
#85000
1'
11
1&
10
#90000
0'
01
0&
00
b111 #
b111 -
b10101011 (
b10101011 2
b1000 "
b1000 ,
#95000
1'
11
1&
10
#100000
0'
01
0&
00
b1000 #
b1000 -
b10101 (
b10101 2
b1001 "
b1001 ,
#105000
1'
11
1&
10
#110000
0'
01
0&
00
b1001 #
b1001 -
b11110001 (
b11110001 2
b1010 "
b1010 ,
